{
  "slug": "lars-brownworth",
  "guest": "Lars Brownworth",
  "title_en": "Byzantine Empire, Vikings, and the Art of History",
  "title_zh": "拉尔斯·布朗沃斯谈拜占庭帝国、维京人与历史的艺术",
  "summary_zh": "这是 Lex Fridman 与历史播客人、作家拉尔斯·布朗沃斯的对话。布朗沃斯以让拜占庭帝国和中世纪历史变得生动有趣著称，他分享了历史叙事的技艺，以及从这些「被遗忘的帝国」中汲取的对当代文明的洞察。",
  "key_points_zh": [
    "拜占庭帝国的被遗忘遗产：布朗沃斯认为拜占庭帝国（东罗马帝国，395-1453年）是历史上最被低估的文明之一，它保存了古希腊罗马知识超过一千年，直接促成了文艺复兴。西方历史教育中对拜占庭的忽视，导致了对中世纪历史的严重误解。",
    "历史叙事的技艺：布朗沃斯认为历史的价值在于故事，而非枯燥的事实清单。他分享了如何将复杂的历史事件转化为引人入胜的叙事，让更多人能够接触和理解历史，这是他的播客和著作的核心哲学。",
    "维京人的真实面貌：布朗沃斯著有《北方人》，纠正了维京人只是野蛮入侵者的刻板印象——他们同时是出色的商人、探险家和外交官，在中东、拜占庭和北美都留下了深刻影响。",
    "帝国的兴衰模式：布朗沃斯从多个古代帝国的历史中提炼了兴衰模式——内部腐败、边境压力、精英阶层的自利，以及对创始意义的遗忘。他认为这些模式对理解当代政治有直接的启示价值。",
    "历史与当代的对话：布朗沃斯认为学习历史不是为了了解过去，而是为了理解人类行为的基本模式——这些模式在不同时代和文化中反复出现，是「免费的人生经验」。"
  ],
  "topics_zh": ["拜占庭帝国", "维京人历史", "历史叙事", "中世纪", "帝国兴衰", "历史教育", "文艺复兴前史"],
  "notable_quotes_zh": [
    "布朗沃斯：拜占庭保存了古典世界的知识超过一千年，然后在君士坦丁堡陷落时把这些知识带到了意大利，点燃了文艺复兴——我们欠拜占庭的债比大多数人意识到的要多得多。",
    "布朗沃斯：历史的价值不在于记住日期，而在于理解人类——当你读到 1000 年前的政治失败，你认出了你今天看到的同样模式。",
    "布朗沃斯：维京人是历史上最被误解的民族之一——他们不只是战士，他们是第一批真正的全球化者。"
  ],
  "guest_intro_zh": "拉尔斯·布朗沃斯（Lars Brownworth）是美国历史播客人和作家，以「12 Byzantine Rulers」播客开创了历史播客这一形式，著有《拜占庭失落的帝国》和《北方人：维京人的历史》。他以将复杂历史变得引人入胜和易于理解著称。"
}
