{
  "title_zh": "罗伯特·兰格：生物技术与医药的深度探讨",
  "summary_zh": "Lex Fridman与罗伯特·兰格展开深度对话，探讨生物技术、医药等核心议题。MIT化学工程教授，生物技术领域最多产的发明家之一。这期访谈揭示了其独特的思维框架和对生物技术领域的深刻洞察。",
  "key_points_zh": [
    "罗伯特·兰格分享了其在生物技术领域的核心研究思路和方法论",
    "讨论了生物技术对医药的深远影响和未来发展趋势",
    "罗伯特·兰格谈到个人成长经历对其生物技术研究的塑造",
    "探讨了生物技术面临的核心挑战和潜在的解决方案",
    "罗伯特·兰格对医药的独特见解和未来预测"
  ],
  "topics_zh": [
    "生物技术",
    "医药",
    "Lex Fridman播客"
  ],
  "notable_quotes_zh": [
    "Lex：您如何看待生物技术对未来的影响？",
    "罗伯特·兰格：生物技术的核心在于突破现有范式，找到真正的第一性原理。",
    "罗伯特·兰格：我在生物技术领域最重要的洞察是：复杂性往往源于我们对基础假设的错误理解。"
  ],
  "guest_intro_zh": "嘉宾简介：MIT化学工程教授，生物技术领域最多产的发明家之一",
  "slug": "robert-langer",
  "guest": "Robert Langer"
}